spark_parser/__init__.py
spark_parser/ast.py
spark_parser/scanner.py
spark_parser/spark.py
spark_parser/version.py
spark_parser-1.8.9.data/scripts/spark-parser-coverage
spark_parser-1.8.9.dist-info/LICENSE
spark_parser-1.8.9.dist-info/METADATA
spark_parser-1.8.9.dist-info/WHEEL
spark_parser-1.8.9.dist-info/top_level.txt
spark_parser-1.8.9.dist-info/zip-safe
spark_parser-1.8.9.dist-info/RECORD
